oremda/cli/__init__.py
oremda/cli/pull.py
oremda/cli/run.py
oremda_cli-0.0.2.dist-info/entry_points.txt
oremda_cli-0.0.2.dist-info/WHEEL
oremda_cli-0.0.2.dist-info/METADATA
oremda_cli-0.0.2.dist-info/RECORD
