Metadata-Version: 2.1
Name: oremda-cli
Version: 0.0.2
Summary: 
License: BSD-3-Clause
Author: Alessandro Genova
Author-email: alessandro.genova@kitware.com
Requires-Python: >=3.8,<4.0
Classifier: License :: OSI Approved :: BSD License
Classifier: Programming Language :: Python :: 3
Classifier: Programming Language :: Python :: 3.10
Classifier: Programming Language :: Python :: 3.8
Classifier: Programming Language :: Python :: 3.9
Requires-Dist: click (>=8.0.3,<9.0.0)
Requires-Dist: click-plugins (>=1.1.1,<2.0.0)
Requires-Dist: coloredlogs (>=15.0.1,<16.0.0)
Requires-Dist: docker (>=5.0.3,<6.0.0)
Requires-Dist: oremda-core (>=0.0.2,<0.0.3)
Requires-Dist: requests (>=2.27.1,<3.0.0)
Requires-Dist: spython (>=0.1.17,<0.2.0)
